{
    "restaurants": [
        {
            "id": 1,
            "name": "Burger King",
            "img": "https://imageproxy.wolt.com/venue/5b0561031daef7000b6f36db/ab7956bb3b1112bacd46789476c9c7e3",
            "alt": "Burger King",
            "description": "Burgers",
            "path": "/"
        },
        {
            "id": 2,
            "name": "Taco Bell",
            "img": "https://imageproxy.wolt.com/venue/6124ddcd9a901a98c6a5ed5d/75f0fe12-0a1d-11ec-b6c2-e686f90804b3_7487c59e28f78880753406a4315752b8.jpeg",
            "alt": "Taco Bell",
            "description": "Mexican",
            "path": "/"
        },
        {
            "id": 3,
            "name": "McDonald's",
            "img": "https://imageproxy.wolt.com/venue/5e83518df638003969216699/6207fc18-b313-11eb-8480-1acefe1e773f_mcd_wolt_etusivu_1010x544.png",
            "alt":" McDonald's",
            "description": "I'm lovin' it",
            "path": "/"
        },
        {
            "id": 4,
            "name": "Friends & Brgrs",
            "img": "https://imageproxy.wolt.com/venue/5ccc20076f16c13303ca12e9/68d3356e-80bc-11eb-8b35-2abc3ccdb078_uusi_feedikuva__1_.jpg",
            "alt": "Friends & Brgrs",
            "description": "Burgers",
            "path": "/"
        },
        {
            "id": 5,
            "name": "Hai Long",
            "img": "https://imageproxy.wolt.com/venue/58f658efff59a629eb533286/6540f8db40d780c56ef3b00f27502047",
            "alt": "Hai Long",
            "description": "Asian",
            "path": "/"
        },
        {
            "id": 6,
            "name": "Picnic",
            "img": "https://imageproxy.wolt.com/venue/59ce1d5b8c9e7d24fca64c82/fae0388c-e209-11ea-b577-1ea5ebfc55c9_picnic.jpeg",
            "alt": "Picnic",
            "description": "Fresh",
            "path": "/"
        }
    ],
    "users": [
        {
            "id": 0,
            "name": "Mori",
            "password": "test",
            "path": "/"
        },
        {
            "id": 1,
            "name": "user",
            "password": "test",
            "path": "/"
        }
    ]
}